{
  "status": "APERTO",
  "open": true,
  "values": {
    "source": "ls-tc.de",
    "data": [
      {
        "symbol": "VUAA",
        "label": "S&P 500",
        "price": 111.6075,
        "dailyChange": "-0.74",
        "value": 111.6075,
        "v1": "-0.74%D",
        "v2": "-1.28%W",
        "v3": "-1.07%M",
        "v_led": "-1.07%M",
        "v_alert": "-1.07%M",
        "v_bot": "-1.07%M"
      },
      {
        "symbol": "VNGA80",
        "label": "LifeStrategy 80",
        "price": 39.57,
        "dailyChange": "-0.53",
        "value": 39.57,
        "v1": "-0.53%D",
        "v2": "-0.95%W",
        "v3": "+0.48%M",
        "v_led": "+0.48%M",
        "v_alert": "+0.48%M",
        "v_bot": "+0.48%M"
      },
      {
        "symbol": "GOLD",
        "label": "Physical Gold",
        "price": 177.34,
        "dailyChange": "-1.13",
        "value": 177.34,
        "v1": "-1.13%D",
        "v2": "+6.88%W",
        "v3": "+19.45%M",
        "v_led": "+19.45%M",
        "v_alert": "+19.45%M",
        "v_bot": "+19.45%M"
      },
      {
        "symbol": "XEON",
        "label": "XEON",
        "price": 148.2695,
        "dailyChange": "-0.01",
        "value": 148.2695,
        "v1": "-0.01%D",
        "v2": "+0.03%W",
        "v3": "+0.14%M",
        "v_led": "+0.14%M",
        "v_alert": "+0.14%M",
        "v_bot": "+0.14%M"
      },
      {
        "symbol": "VWCE",
        "label": "FTSE All World",
        "price": 146.86,
        "dailyChange": "-0.46",
        "value": 146.86,
        "v1": "-0.46%D",
        "v2": "-0.54%W",
        "v3": "+1.02%M",
        "v_led": "+1.02%M",
        "v_alert": "+1.02%M",
        "v_bot": "+1.02%M"
      },
      {
        "symbol": "EXUS",
        "label": "MSCI World Ex-USA",
        "price": 36.4525,
        "dailyChange": "+0.78",
        "value": 36.4525,
        "v1": "+0.78%D",
        "v2": "+0.39%W",
        "v3": "+3.59%M",
        "v_led": "+3.59%M",
        "v_alert": "+3.59%M",
        "v_bot": "+3.59%M"
      },
      {
        "symbol": "EIMI",
        "label": "Emerging Markets",
        "price": 41.3635,
        "dailyChange": "-1.07",
        "value": 41.3635,
        "v1": "-1.07%D",
        "v2": "+0.69%W",
        "v3": "N/A",
        "v_led": "N/A",
        "v_alert": "N/A",
        "v_bot": "N/A"
      }
    ]
  },
  "last_updated": {
    "iso": "2026-01-29T21:25:20.488895+01:00",
    "readable": "21:25 29-01-2026"
  }
}