{
  "status": "APERTO",
  "open": true,
  "values": {
    "source": "ls-tc.de",
    "data": [
      {
        "symbol": "VUAA",
        "label": "S&P 500",
        "price": 111.9175,
        "dailyChange": "+0.32",
        "value": 111.9175,
        "v1": "+0.32%D",
        "v2": "-2.04%W",
        "v3": "-0.42%M",
        "v_led": "-0.42%M",
        "v_alert": "-0.42%M",
        "v_bot": "-0.42%M"
      },
      {
        "symbol": "VNGA80",
        "label": "LifeStrategy 80",
        "price": 39.5475,
        "dailyChange": "+0.43",
        "value": 39.5475,
        "v1": "+0.43%D",
        "v2": "-1.40%W",
        "v3": "+1.03%M",
        "v_led": "+1.03%M",
        "v_alert": "+1.03%M",
        "v_bot": "+1.03%M"
      },
      {
        "symbol": "GOLD",
        "label": "Physical Gold",
        "price": 164.57,
        "dailyChange": "+2.07",
        "value": 164.57,
        "v1": "+2.07%D",
        "v2": "+4.55%W",
        "v3": "+9.79%M",
        "v_led": "+9.79%M",
        "v_alert": "+9.79%M",
        "v_bot": "+9.79%M"
      },
      {
        "symbol": "XEON",
        "label": "XEON",
        "price": 148.193,
        "dailyChange": "+0.00",
        "value": 148.193,
        "v1": "+0.00%D",
        "v2": "+0.03%W",
        "v3": "+0.15%M",
        "v_led": "+0.15%M",
        "v_alert": "+0.15%M",
        "v_bot": "+0.15%M"
      },
      {
        "symbol": "VWCE",
        "label": "FTSE All World",
        "price": 146.25,
        "dailyChange": "+0.41",
        "value": 146.25,
        "v1": "+0.41%D",
        "v2": "-1.71%W",
        "v3": "+1.27%M",
        "v_led": "+1.27%M",
        "v_alert": "+1.27%M",
        "v_bot": "+1.27%M"
      },
      {
        "symbol": "EXUS",
        "label": "MSCI World Ex-USA",
        "price": 35.8925,
        "dailyChange": "+0.26",
        "value": 35.8925,
        "v1": "+0.26%D",
        "v2": "-1.50%W",
        "v3": "+2.80%M",
        "v_led": "+2.80%M",
        "v_alert": "+2.80%M",
        "v_bot": "+2.80%M"
      },
      {
        "symbol": "EIMI",
        "label": "Emerging Markets",
        "price": 40.4105,
        "dailyChange": "+0.42",
        "value": 40.4105,
        "v1": "+0.42%D",
        "v2": "-0.83%W",
        "v3": "N/A",
        "v_led": "N/A",
        "v_alert": "N/A",
        "v_bot": "N/A"
      }
    ]
  },
  "last_updated": {
    "iso": "2026-01-21T10:10:23.679864+01:00",
    "readable": "10:10 21-01-2026"
  }
}