{
  "status": "APERTO",
  "open": true,
  "values": {
    "source": "ls-tc.de",
    "data": [
      {
        "symbol": "VUAA",
        "label": "S&P 500",
        "price": 112.4225,
        "dailyChange": "+0.96",
        "value": 112.4225,
        "v1": "+0.96%D",
        "v2": "-0.76%W",
        "v3": "-0.31%M",
        "v_led": "-0.31%M",
        "v_alert": "-0.31%M",
        "v_bot": "-0.31%M"
      },
      {
        "symbol": "VNGA80",
        "label": "LifeStrategy 80",
        "price": 39.79,
        "dailyChange": "-0.08",
        "value": 39.79,
        "v1": "-0.08%D",
        "v2": "-0.05%W",
        "v3": "+1.04%M",
        "v_led": "+1.04%M",
        "v_alert": "+1.04%M",
        "v_bot": "+1.04%M"
      },
      {
        "symbol": "GOLD",
        "label": "Physical Gold",
        "price": 175.025,
        "dailyChange": "+2.62",
        "value": 175.025,
        "v1": "+2.62%D",
        "v2": "+6.85%W",
        "v3": "+20.04%M",
        "v_led": "+20.04%M",
        "v_alert": "+20.04%M",
        "v_bot": "+20.04%M"
      },
      {
        "symbol": "XEON",
        "label": "XEON",
        "price": 148.2795,
        "dailyChange": "-0.00",
        "value": 148.2795,
        "v1": "-0.00%D",
        "v2": "+0.05%W",
        "v3": "+0.18%M",
        "v_led": "+0.18%M",
        "v_alert": "+0.18%M",
        "v_bot": "+0.18%M"
      },
      {
        "symbol": "VWCE",
        "label": "FTSE All World",
        "price": 147.34,
        "dailyChange": "+0.71",
        "value": 147.34,
        "v1": "+0.71%D",
        "v2": "-0.51%W",
        "v3": "+1.49%M",
        "v_led": "+1.49%M",
        "v_alert": "+1.49%M",
        "v_bot": "+1.49%M"
      },
      {
        "symbol": "EXUS",
        "label": "MSCI World Ex-USA",
        "price": 36.1225,
        "dailyChange": "-1.06",
        "value": 36.1225,
        "v1": "-1.06%D",
        "v2": "-0.57%W",
        "v3": "+2.95%M",
        "v_led": "+2.95%M",
        "v_alert": "+2.95%M",
        "v_bot": "+2.95%M"
      },
      {
        "symbol": "EIMI",
        "label": "Emerging Markets",
        "price": 41.415,
        "dailyChange": "+0.30",
        "value": 41.415,
        "v1": "+0.30%D",
        "v2": "+1.21%W",
        "v3": "N/A",
        "v_led": "N/A",
        "v_alert": "N/A",
        "v_bot": "N/A"
      }
    ]
  },
  "last_updated": {
    "iso": "2026-01-28T16:40:21.865355+01:00",
    "readable": "16:40 28-01-2026"
  }
}