{
  "status": "APERTO",
  "open": true,
  "values": {
    "source": "ls-tc.de",
    "data": [
      {
        "symbol": "VUAA",
        "label": "S&P 500",
        "price": 115.3925,
        "dailyChange": "+1.00",
        "value": 115.3925,
        "v1": "+1.00%D",
        "v2": "+0.90%W",
        "v3": "+3.99%M",
        "v_led": "+3.99%M"
      },
      {
        "symbol": "VNGA80",
        "label": "LifeStrategy 80",
        "price": 40.46,
        "dailyChange": "+0.87",
        "value": 40.46,
        "v1": "+0.87%D",
        "v2": "+1.33%W",
        "v3": "+4.18%M",
        "v_led": "+4.18%M"
      },
      {
        "symbol": "GOLD",
        "label": "Physical Gold",
        "price": 157.585,
        "dailyChange": "+0.11",
        "value": 157.585,
        "v1": "+0.11%D",
        "v2": "+3.46%W",
        "v3": "+8.61%M",
        "v_led": "+8.61%M"
      },
      {
        "symbol": "XEON",
        "label": "XEON",
        "price": 148.177,
        "dailyChange": "+0.02",
        "value": 148.177,
        "v1": "+0.02%D",
        "v2": "+0.04%W",
        "v3": "+0.19%M",
        "v_led": "+0.19%M"
      },
      {
        "symbol": "VWCE",
        "label": "FTSE All World",
        "price": 150.18,
        "dailyChange": "+0.93",
        "value": 150.18,
        "v1": "+0.93%D",
        "v2": "+1.36%W",
        "v3": "+5.28%M",
        "v_led": "+5.28%M"
      },
      {
        "symbol": "EXUS",
        "label": "MSCI World Ex-USA",
        "price": 36.745,
        "dailyChange": "+0.84",
        "value": 36.745,
        "v1": "+0.84%D",
        "v2": "+2.13%W",
        "v3": "+6.50%M",
        "v_led": "+6.50%M"
      },
      {
        "symbol": "EIMI",
        "label": "Emerging Markets",
        "price": 41.1905,
        "dailyChange": "+1.08",
        "value": 41.1905,
        "v1": "+1.08%D",
        "v2": "+2.90%W",
        "v3": "N/A",
        "v_led": "N/A"
      }
    ]
  },
  "last_updated": {
    "iso": "2026-01-15T19:55:23.898053+01:00",
    "readable": "19:55 15-01-2026"
  }
}