{
  "status": "APERTO",
  "open": true,
  "values": {
    "source": "ls-tc.de",
    "data": [
      {
        "symbol": "VUAA",
        "label": "S&P 500",
        "price": 113.3225,
        "dailyChange": "+0.04",
        "value": 113.3225,
        "v1": "+0.04%D",
        "v2": "-1.48%W",
        "v3": "+1.11%M",
        "v_led": "+1.11%M",
        "v_alert": "+1.11%M",
        "v_bot": "+1.11%M"
      },
      {
        "symbol": "VNGA80",
        "label": "LifeStrategy 80",
        "price": 39.9625,
        "dailyChange": "+0.38",
        "value": 39.9625,
        "v1": "+0.38%D",
        "v2": "-0.91%W",
        "v3": "+2.09%M",
        "v_led": "+2.09%M",
        "v_alert": "+2.09%M",
        "v_bot": "+2.09%M"
      },
      {
        "symbol": "GOLD",
        "label": "Physical Gold",
        "price": 164.505,
        "dailyChange": "+0.42",
        "value": 164.505,
        "v1": "+0.42%D",
        "v2": "+4.40%W",
        "v3": "+8.94%M",
        "v_led": "+8.94%M",
        "v_alert": "+8.94%M",
        "v_bot": "+8.94%M"
      },
      {
        "symbol": "XEON",
        "label": "XEON",
        "price": 148.212,
        "dailyChange": "+0.00",
        "value": 148.212,
        "v1": "+0.00%D",
        "v2": "+0.03%W",
        "v3": "+0.15%M",
        "v_led": "+0.15%M",
        "v_alert": "+0.15%M",
        "v_bot": "+0.15%M"
      },
      {
        "symbol": "VWCE",
        "label": "FTSE All World",
        "price": 147.98,
        "dailyChange": "-0.07",
        "value": 147.98,
        "v1": "-0.07%D",
        "v2": "-1.15%W",
        "v3": "+2.54%M",
        "v_led": "+2.54%M",
        "v_alert": "+2.54%M",
        "v_bot": "+2.54%M"
      },
      {
        "symbol": "EXUS",
        "label": "MSCI World Ex-USA",
        "price": 36.1875,
        "dailyChange": "-0.39",
        "value": 36.1875,
        "v1": "-0.39%D",
        "v2": "-1.07%W",
        "v3": "+3.38%M",
        "v_led": "+3.38%M",
        "v_alert": "+3.38%M",
        "v_bot": "+3.38%M"
      },
      {
        "symbol": "EIMI",
        "label": "Emerging Markets",
        "price": 41.06,
        "dailyChange": "+0.34",
        "value": 41.06,
        "v1": "+0.34%D",
        "v2": "-0.22%W",
        "v3": "N/A",
        "v_led": "N/A",
        "v_alert": "N/A",
        "v_bot": "N/A"
      }
    ]
  },
  "last_updated": {
    "iso": "2026-01-22T17:40:21.005129+01:00",
    "readable": "17:40 22-01-2026"
  }
}