{
  "status": "APERTO",
  "open": true,
  "values": {
    "source": "ls-tc.de",
    "data": [
      {
        "symbol": "VUAA",
        "label": "S&P 500",
        "price": 112.4975,
        "dailyChange": "+1.86",
        "value": 112.4975,
        "v1": "+1.86%D",
        "v2": "+0.08%W",
        "v3": "-1.21%M",
        "v_led": "-1.21%M",
        "v_alert": "-1.21%M",
        "v_bot": "-1.21%M"
      },
      {
        "symbol": "VNGA80",
        "label": "LifeStrategy 80",
        "price": 39.9675,
        "dailyChange": "+1.06",
        "value": 39.9675,
        "v1": "+1.06%D",
        "v2": "+0.40%W",
        "v3": "+0.32%M",
        "v_led": "+0.32%M",
        "v_alert": "+0.32%M",
        "v_bot": "+0.32%M"
      },
      {
        "symbol": "GOLD",
        "label": "Physical Gold",
        "price": 165.935,
        "dailyChange": "+3.51",
        "value": 165.935,
        "v1": "+3.51%D",
        "v2": "+2.83%W",
        "v3": "+9.52%M",
        "v_led": "+9.52%M",
        "v_alert": "+9.52%M",
        "v_bot": "+9.52%M"
      },
      {
        "symbol": "XEON",
        "label": "XEON",
        "price": 148.355,
        "dailyChange": "+0.00",
        "value": 148.355,
        "v1": "+0.00%D",
        "v2": "+0.04%W",
        "v3": "+0.18%M",
        "v_led": "+0.18%M",
        "v_alert": "+0.18%M",
        "v_bot": "+0.18%M"
      },
      {
        "symbol": "VWCE",
        "label": "FTSE All World",
        "price": 148.14,
        "dailyChange": "+1.86",
        "value": 148.14,
        "v1": "+1.86%D",
        "v2": "+0.62%W",
        "v3": "+0.36%M",
        "v_led": "+0.36%M",
        "v_alert": "+0.36%M",
        "v_bot": "+0.36%M"
      },
      {
        "symbol": "EXUS",
        "label": "MSCI World Ex-USA",
        "price": 36.885,
        "dailyChange": "+1.61",
        "value": 36.885,
        "v1": "+1.61%D",
        "v2": "+1.84%W",
        "v3": "+2.97%M",
        "v_led": "+2.97%M",
        "v_alert": "+2.97%M",
        "v_bot": "+2.97%M"
      },
      {
        "symbol": "EIMI",
        "label": "Emerging Markets",
        "price": 41.6025,
        "dailyChange": "+1.94",
        "value": 41.6025,
        "v1": "+1.94%D",
        "v2": "+1.62%W",
        "v3": "N/A",
        "v_led": "N/A",
        "v_alert": "N/A",
        "v_bot": "N/A"
      }
    ]
  },
  "last_updated": {
    "iso": "2026-02-06T21:10:23.064061+01:00",
    "readable": "21:10 06-02-2026"
  }
}