{
  "status": "APERTO",
  "open": true,
  "values": {
    "source": "ls-tc.de",
    "data": [
      {
        "symbol": "VUAA",
        "label": "S&P 500",
        "price": 111.8775,
        "dailyChange": "+0.28",
        "value": 111.8775,
        "v1": "+0.28%D",
        "v2": "-2.08%W",
        "v3": "-0.45%M",
        "v_led": "-0.45%M",
        "v_alert": "-0.45%M",
        "v_bot": "-0.45%M"
      },
      {
        "symbol": "VNGA80",
        "label": "LifeStrategy 80",
        "price": 39.535,
        "dailyChange": "+0.39",
        "value": 39.535,
        "v1": "+0.39%D",
        "v2": "-1.43%W",
        "v3": "+1.00%M",
        "v_led": "+1.00%M",
        "v_alert": "+1.00%M",
        "v_bot": "+1.00%M"
      },
      {
        "symbol": "GOLD",
        "label": "Physical Gold",
        "price": 164.8,
        "dailyChange": "+2.21",
        "value": 164.8,
        "v1": "+2.21%D",
        "v2": "+4.69%W",
        "v3": "+9.94%M",
        "v_led": "+9.94%M",
        "v_alert": "+9.94%M",
        "v_bot": "+9.94%M"
      },
      {
        "symbol": "XEON",
        "label": "XEON",
        "price": 148.193,
        "dailyChange": "+0.00",
        "value": 148.193,
        "v1": "+0.00%D",
        "v2": "+0.03%W",
        "v3": "+0.15%M",
        "v_led": "+0.15%M",
        "v_alert": "+0.15%M",
        "v_bot": "+0.15%M"
      },
      {
        "symbol": "VWCE",
        "label": "FTSE All World",
        "price": 146.21,
        "dailyChange": "+0.38",
        "value": 146.21,
        "v1": "+0.38%D",
        "v2": "-1.74%W",
        "v3": "+1.24%M",
        "v_led": "+1.24%M",
        "v_alert": "+1.24%M",
        "v_bot": "+1.24%M"
      },
      {
        "symbol": "EXUS",
        "label": "MSCI World Ex-USA",
        "price": 35.89,
        "dailyChange": "+0.25",
        "value": 35.89,
        "v1": "+0.25%D",
        "v2": "-1.51%W",
        "v3": "+2.79%M",
        "v_led": "+2.79%M",
        "v_alert": "+2.79%M",
        "v_bot": "+2.79%M"
      },
      {
        "symbol": "EIMI",
        "label": "Emerging Markets",
        "price": 40.4175,
        "dailyChange": "+0.44",
        "value": 40.4175,
        "v1": "+0.44%D",
        "v2": "-0.82%W",
        "v3": "N/A",
        "v_led": "N/A",
        "v_alert": "N/A",
        "v_bot": "N/A"
      }
    ]
  },
  "last_updated": {
    "iso": "2026-01-21T10:25:25.490560+01:00",
    "readable": "10:25 21-01-2026"
  }
}