{
  "status": "APERTO",
  "open": true,
  "values": {
    "source": "ls-tc.de",
    "data": [
      {
        "symbol": "VUAA",
        "label": "S&P 500",
        "price": 112.14,
        "dailyChange": "-0.15",
        "value": 112.14,
        "v1": "-0.15%D",
        "v2": "-1.21%W",
        "v3": "-0.42%M",
        "v_led": "-0.42%M",
        "v_alert": "-0.42%M",
        "v_bot": "-0.42%M"
      },
      {
        "symbol": "VNGA80",
        "label": "LifeStrategy 80",
        "price": 39.74,
        "dailyChange": "-0.23",
        "value": 39.74,
        "v1": "-0.23%D",
        "v2": "-0.85%W",
        "v3": "+1.17%M",
        "v_led": "+1.17%M",
        "v_alert": "+1.17%M",
        "v_bot": "+1.17%M"
      },
      {
        "symbol": "GOLD",
        "label": "Physical Gold",
        "price": 169.515,
        "dailyChange": "+1.60",
        "value": 169.515,
        "v1": "+1.60%D",
        "v2": "+6.24%W",
        "v3": "+11.89%M",
        "v_led": "+11.89%M",
        "v_alert": "+11.89%M",
        "v_bot": "+11.89%M"
      },
      {
        "symbol": "XEON",
        "label": "XEON",
        "price": 148.237,
        "dailyChange": "-0.00",
        "value": 148.237,
        "v1": "-0.00%D",
        "v2": "+0.04%W",
        "v3": "+0.17%M",
        "v_led": "+0.17%M",
        "v_alert": "+0.17%M",
        "v_bot": "+0.17%M"
      },
      {
        "symbol": "VWCE",
        "label": "FTSE All World",
        "price": 146.85,
        "dailyChange": "-0.04",
        "value": 146.85,
        "v1": "-0.04%D",
        "v2": "-0.96%W",
        "v3": "+1.38%M",
        "v_led": "+1.38%M",
        "v_alert": "+1.38%M",
        "v_bot": "+1.38%M"
      },
      {
        "symbol": "EXUS",
        "label": "MSCI World Ex-USA",
        "price": 36.195,
        "dailyChange": "-0.43",
        "value": 36.195,
        "v1": "-0.43%D",
        "v2": "-0.62%W",
        "v3": "+3.15%M",
        "v_led": "+3.15%M",
        "v_alert": "+3.15%M",
        "v_bot": "+3.15%M"
      },
      {
        "symbol": "EIMI",
        "label": "Emerging Markets",
        "price": 40.731,
        "dailyChange": "-0.73",
        "value": 40.731,
        "v1": "-0.73%D",
        "v2": "-0.99%W",
        "v3": "N/A",
        "v_led": "N/A",
        "v_alert": "N/A",
        "v_bot": "N/A"
      }
    ]
  },
  "last_updated": {
    "iso": "2026-01-26T14:40:23.100724+01:00",
    "readable": "14:40 26-01-2026"
  }
}