{
  "status": "APERTO",
  "open": true,
  "values": {
    "source": "ls-tc.de",
    "data": [
      {
        "symbol": "VUAA",
        "label": "S&P 500",
        "price": 112.305,
        "dailyChange": "-0.24",
        "value": 112.305,
        "v1": "-0.24%D",
        "v2": "+0.29%W",
        "v3": "-1.64%M",
        "v_led": "-1.64%M",
        "v_alert": "-1.64%M",
        "v_bot": "-1.64%M"
      },
      {
        "symbol": "VNGA80",
        "label": "LifeStrategy 80",
        "price": 39.8675,
        "dailyChange": "-0.13",
        "value": 39.8675,
        "v1": "-0.13%D",
        "v2": "+0.62%W",
        "v3": "-0.53%M",
        "v_led": "-0.53%M",
        "v_alert": "-0.53%M",
        "v_bot": "-0.53%M"
      },
      {
        "symbol": "GOLD",
        "label": "Physical Gold",
        "price": 165.295,
        "dailyChange": "-0.85",
        "value": 165.295,
        "v1": "-0.85%D",
        "v2": "-7.95%W",
        "v3": "+8.30%M",
        "v_led": "+8.30%M",
        "v_alert": "+8.30%M",
        "v_bot": "+8.30%M"
      },
      {
        "symbol": "XEON",
        "label": "XEON",
        "price": 148.344,
        "dailyChange": "+0.00",
        "value": 148.344,
        "v1": "+0.00%D",
        "v2": "+0.05%W",
        "v3": "+0.16%M",
        "v_led": "+0.16%M",
        "v_alert": "+0.16%M",
        "v_bot": "+0.16%M"
      },
      {
        "symbol": "VWCE",
        "label": "FTSE All World",
        "price": 147.61,
        "dailyChange": "-0.28",
        "value": 147.61,
        "v1": "-0.28%D",
        "v2": "+0.12%W",
        "v3": "-0.43%M",
        "v_led": "-0.43%M",
        "v_alert": "-0.43%M",
        "v_bot": "-0.43%M"
      },
      {
        "symbol": "EXUS",
        "label": "MSCI World Ex-USA",
        "price": 36.6625,
        "dailyChange": "-0.59",
        "value": 36.6625,
        "v1": "-0.59%D",
        "v2": "+0.45%W",
        "v3": "+1.81%M",
        "v_led": "+1.81%M",
        "v_alert": "+1.81%M",
        "v_bot": "+1.81%M"
      },
      {
        "symbol": "EIMI",
        "label": "Emerging Markets",
        "price": 41.1405,
        "dailyChange": "+0.34",
        "value": 41.1405,
        "v1": "+0.34%D",
        "v2": "-0.79%W",
        "v3": "N/A",
        "v_led": "N/A",
        "v_alert": "N/A",
        "v_bot": "N/A"
      }
    ]
  },
  "last_updated": {
    "iso": "2026-02-05T09:10:24.116532+01:00",
    "readable": "09:10 05-02-2026"
  }
}