{
  "status": "APERTO",
  "open": true,
  "values": {
    "source": "ls-tc.de",
    "data": [
      {
        "symbol": "VUAA",
        "label": "S&P 500",
        "price": 112.105,
        "dailyChange": "-0.28",
        "value": 112.105,
        "v1": "-0.28%D",
        "v2": "+0.49%W",
        "v3": "-0.45%M",
        "v_led": "-0.45%M",
        "v_alert": "-0.45%M",
        "v_bot": "-0.45%M"
      },
      {
        "symbol": "VNGA80",
        "label": "LifeStrategy 80",
        "price": 39.7775,
        "dailyChange": "-0.23",
        "value": 39.7775,
        "v1": "-0.23%D",
        "v2": "+1.01%W",
        "v3": "+1.27%M",
        "v_led": "+1.27%M",
        "v_alert": "+1.27%M",
        "v_bot": "+1.27%M"
      },
      {
        "symbol": "GOLD",
        "label": "Physical Gold",
        "price": 167.86,
        "dailyChange": "+0.44",
        "value": 167.86,
        "v1": "+0.44%D",
        "v2": "+4.11%W",
        "v3": "+10.80%M",
        "v_led": "+10.80%M",
        "v_alert": "+10.80%M",
        "v_bot": "+10.80%M"
      },
      {
        "symbol": "XEON",
        "label": "XEON",
        "price": 148.2735,
        "dailyChange": "+0.02",
        "value": 148.2735,
        "v1": "+0.02%D",
        "v2": "+0.06%W",
        "v3": "+0.19%M",
        "v_led": "+0.19%M",
        "v_alert": "+0.19%M",
        "v_bot": "+0.19%M"
      },
      {
        "symbol": "VWCE",
        "label": "FTSE All World",
        "price": 147.14,
        "dailyChange": "-0.17",
        "value": 147.14,
        "v1": "-0.17%D",
        "v2": "+1.02%W",
        "v3": "+1.58%M",
        "v_led": "+1.58%M",
        "v_alert": "+1.58%M",
        "v_bot": "+1.58%M"
      },
      {
        "symbol": "EXUS",
        "label": "MSCI World Ex-USA",
        "price": 36.305,
        "dailyChange": "+0.40",
        "value": 36.305,
        "v1": "+0.40%D",
        "v2": "+1.41%W",
        "v3": "+3.46%M",
        "v_led": "+3.46%M",
        "v_alert": "+3.46%M",
        "v_bot": "+3.46%M"
      },
      {
        "symbol": "EIMI",
        "label": "Emerging Markets",
        "price": 41.1135,
        "dailyChange": "+0.42",
        "value": 41.1135,
        "v1": "+0.42%D",
        "v2": "+2.17%W",
        "v3": "N/A",
        "v_led": "N/A",
        "v_alert": "N/A",
        "v_bot": "N/A"
      }
    ]
  },
  "last_updated": {
    "iso": "2026-01-27T16:10:26.287946+01:00",
    "readable": "16:10 27-01-2026"
  }
}