{
  "status": "APERTO",
  "open": true,
  "values": {
    "source": "ls-tc.de",
    "data": [
      {
        "symbol": "VUAA",
        "label": "S&P 500",
        "price": 113.6925,
        "dailyChange": "-0.16",
        "value": 113.6925,
        "v1": "-0.16%D",
        "v2": "+0.78%W",
        "v3": "+0.78%W",
        "v_led": "+0.78%W"
      },
      {
        "symbol": "VNGA80",
        "label": "LifeStrategy 80",
        "price": 39.825,
        "dailyChange": "-0.04",
        "value": 39.825,
        "v1": "-0.04%D",
        "v2": "+1.13%W",
        "v3": "+1.13%W",
        "v_led": "+1.13%W"
      },
      {
        "symbol": "GOLD",
        "label": "Physical Gold",
        "price": 150.09,
        "dailyChange": "-0.94",
        "value": 150.09,
        "v1": "-0.94%D",
        "v2": "+1.10%W",
        "v3": "+1.10%W",
        "v_led": "+1.10%W"
      },
      {
        "symbol": "XEON",
        "label": "XEON",
        "price": 148.119,
        "dailyChange": "+0.02",
        "value": 148.119,
        "v1": "+0.02%D",
        "v2": "+0.04%W",
        "v3": "+0.04%W",
        "v_led": "+0.04%W"
      },
      {
        "symbol": "VWCE",
        "label": "FTSE All World",
        "price": 147.37,
        "dailyChange": "-0.16",
        "value": 147.37,
        "v1": "-0.16%D",
        "v2": "+1.37%W",
        "v3": "+1.37%W",
        "v_led": "+1.37%W"
      },
      {
        "symbol": "EXUS",
        "label": "MSCI World Ex-USA",
        "price": 35.7175,
        "dailyChange": "-0.29",
        "value": 35.7175,
        "v1": "-0.29%D",
        "v2": "+1.50%W",
        "v3": "+1.50%W",
        "v_led": "+1.50%W"
      },
      {
        "symbol": "EIMI",
        "label": "Emerging Markets",
        "price": 39.866,
        "dailyChange": "-",
        "value": 39.866,
        "v1": "N/A",
        "v2": "N/A",
        "v3": "N/A",
        "v_led": "N/A"
      }
    ]
  },
  "last_updated": {
    "iso": "2026-01-08T13:00:37.368941+01:00",
    "readable": "13:00 08-01-2026"
  }
}