{
  "status": "APERTO",
  "open": true,
  "values": {
    "source": "ls-tc.de",
    "data": [
      {
        "symbol": "VUAA",
        "label": "S&P 500",
        "price": 111.6175,
        "dailyChange": "-0.85",
        "value": 111.6175,
        "v1": "-0.85%D",
        "v2": "-0.32%W",
        "v3": "-2.24%M",
        "v_led": "-2.24%M",
        "v_alert": "-2.24%M",
        "v_bot": "-2.24%M"
      },
      {
        "symbol": "VNGA80",
        "label": "LifeStrategy 80",
        "price": 39.6525,
        "dailyChange": "-0.67",
        "value": 39.6525,
        "v1": "-0.67%D",
        "v2": "+0.08%W",
        "v3": "-1.07%M",
        "v_led": "-1.07%M",
        "v_alert": "-1.07%M",
        "v_bot": "-1.07%M"
      },
      {
        "symbol": "GOLD",
        "label": "Physical Gold",
        "price": 163.25,
        "dailyChange": "-2.08",
        "value": 163.25,
        "v1": "-2.08%D",
        "v2": "-9.09%W",
        "v3": "+6.97%M",
        "v_led": "+6.97%M",
        "v_alert": "+6.97%M",
        "v_bot": "+6.97%M"
      },
      {
        "symbol": "XEON",
        "label": "XEON",
        "price": 148.346,
        "dailyChange": "+0.00",
        "value": 148.346,
        "v1": "+0.00%D",
        "v2": "+0.05%W",
        "v3": "+0.17%M",
        "v_led": "+0.17%M",
        "v_alert": "+0.17%M",
        "v_bot": "+0.17%M"
      },
      {
        "symbol": "VWCE",
        "label": "FTSE All World",
        "price": 146.63,
        "dailyChange": "-0.95",
        "value": 146.63,
        "v1": "-0.95%D",
        "v2": "-0.54%W",
        "v3": "-1.09%M",
        "v_led": "-1.09%M",
        "v_alert": "-1.09%M",
        "v_bot": "-1.09%M"
      },
      {
        "symbol": "EXUS",
        "label": "MSCI World Ex-USA",
        "price": 36.4325,
        "dailyChange": "-1.21",
        "value": 36.4325,
        "v1": "-1.21%D",
        "v2": "-0.18%W",
        "v3": "+1.17%M",
        "v_led": "+1.17%M",
        "v_alert": "+1.17%M",
        "v_bot": "+1.17%M"
      },
      {
        "symbol": "EIMI",
        "label": "Emerging Markets",
        "price": 40.803,
        "dailyChange": "-0.48",
        "value": 40.803,
        "v1": "-0.48%D",
        "v2": "-1.61%W",
        "v3": "N/A",
        "v_led": "N/A",
        "v_alert": "N/A",
        "v_bot": "N/A"
      }
    ]
  },
  "last_updated": {
    "iso": "2026-02-05T13:55:21.367895+01:00",
    "readable": "13:55 05-02-2026"
  }
}