{
  "status": "APERTO",
  "open": true,
  "values": {
    "source": "ls-tc.de",
    "data": [
      {
        "symbol": "VUAA",
        "label": "S&P 500",
        "price": 112.5625,
        "dailyChange": "+0.31",
        "value": 112.5625,
        "v1": "+0.31%D",
        "v2": "+1.68%W",
        "v3": "-0.63%M",
        "v_led": "-0.63%M",
        "v_alert": "-0.63%M",
        "v_bot": "-0.63%M"
      },
      {
        "symbol": "VNGA80",
        "label": "LifeStrategy 80",
        "price": 40.315,
        "dailyChange": "+0.24",
        "value": 40.315,
        "v1": "+0.24%D",
        "v2": "+1.19%W",
        "v3": "+1.27%M",
        "v_led": "+1.27%M",
        "v_alert": "+1.27%M",
        "v_bot": "+1.27%M"
      },
      {
        "symbol": "GOLD",
        "label": "Physical Gold",
        "price": 169.1,
        "dailyChange": "+0.34",
        "value": 169.1,
        "v1": "+0.34%D",
        "v2": "+0.59%W",
        "v3": "+3.23%M",
        "v_led": "+3.23%M",
        "v_alert": "+3.23%M",
        "v_bot": "+3.23%M"
      },
      {
        "symbol": "XEON",
        "label": "XEON",
        "price": 148.466,
        "dailyChange": "-0.00",
        "value": 148.466,
        "v1": "-0.00%D",
        "v2": "+0.03%W",
        "v3": "+0.17%M",
        "v_led": "+0.17%M",
        "v_alert": "+0.17%M",
        "v_bot": "+0.17%M"
      },
      {
        "symbol": "VWCE",
        "label": "FTSE All World",
        "price": 149.67,
        "dailyChange": "+0.31",
        "value": 149.67,
        "v1": "+0.31%D",
        "v2": "+1.62%W",
        "v3": "+1.07%M",
        "v_led": "+1.07%M",
        "v_alert": "+1.07%M",
        "v_bot": "+1.07%M"
      },
      {
        "symbol": "EXUS",
        "label": "MSCI World Ex-USA",
        "price": 37.695,
        "dailyChange": "-0.12",
        "value": 37.695,
        "v1": "-0.12%D",
        "v2": "+0.92%W",
        "v3": "+3.76%M",
        "v_led": "+3.76%M",
        "v_alert": "+3.76%M",
        "v_bot": "+3.76%M"
      },
      {
        "symbol": "EIMI",
        "label": "Emerging Markets",
        "price": 42.648,
        "dailyChange": "-0.12",
        "value": 42.648,
        "v1": "-0.12%D",
        "v2": "+0.99%W",
        "v3": "+4.22%M",
        "v_led": "+4.22%M",
        "v_alert": "+4.22%M",
        "v_bot": "+4.22%M"
      }
    ]
  },
  "last_updated": {
    "iso": "2026-02-20T08:55:19.805576+01:00",
    "readable": "08:55 20-02-2026"
  }
}